{
  "votacionId": "49588",
  "eventoId": "41300",
  "sesion": {
    "eventoId": "41300",
    "tipo": "Ordinaria",
    "numero": "35",
    "descripcion": "No. 35, Fase 1, Fecha 30/09/2025 12:50:22",
    "fecha": "30/09/2025"
  },
  "pregunta": "APROBACIÓN DE MOCIÓN PRIVILEGIADA PARA RETORNO A COMISÍON 6452  (REPRESENTANTE ESTRADA)",
  "iniciativa": null,
  "votos": {
    "favor": [
      {
        "nombre": "Ajcip Canel Hellen Magaly Alexándra",
        "id_diputado": "840"
      },
      {
        "nombre": "Archila Cordón Manuel de Jesús",
        "id_diputado": "907"
      },
      {
        "nombre": "Barrera Robles Raúl Amilcar",
        "id_diputado": "894"
      },
      {
        "nombre": "Bonilla González Víctor Vicente",
        "id_diputado": "891"
      },
      {
        "nombre": "Bran Colindres Ernesto",
        "id_diputado": "900"
      },
      {
        "nombre": "Cardona Arreaga Karla Betzaida",
        "id_diputado": "791"
      },
      {
        "nombre": "Castañón González Manfredo Duvalier",
        "id_diputado": "934"
      },
      {
        "nombre": "Castro Delgado Jorge Romeo",
        "id_diputado": "842"
      },
      {
        "nombre": "Celis Navas Sergio Leonel",
        "id_diputado": "31"
      },
      {
        "nombre": "Chocooj de la Cruz Bequer Neftali",
        "id_diputado": "965"
      },
      {
        "nombre": "Cifuentes Navarro Gustavo Adolfo",
        "id_diputado": "961"
      },
      {
        "nombre": "Crúz Montoya Gustavo Adolfo",
        "id_diputado": "826"
      },
      {
        "nombre": "De León Torres Nadia Lorena",
        "id_diputado": "933"
      },
      {
        "nombre": "Echeverría Casado Herman Otoniel",
        "id_diputado": "884"
      },
      {
        "nombre": "Enriquez Garzaro Sergio Guillermo",
        "id_diputado": "941"
      },
      {
        "nombre": "Estrada Domínguez Julio Héctor",
        "id_diputado": "930"
      },
      {
        "nombre": "Godoy Palala Mirna Victoria",
        "id_diputado": "909"
      },
      {
        "nombre": "Gómez Gómez Julio Pedro",
        "id_diputado": "971"
      },
      {
        "nombre": "Guerrero de la Cruz Alma Luz",
        "id_diputado": "935"
      },
      {
        "nombre": "Guzmán Figueroa Rolando",
        "id_diputado": "902"
      },
      {
        "nombre": "Lima Pop Fidencio",
        "id_diputado": "247"
      },
      {
        "nombre": "Madrazo Mazariegos Danilo",
        "id_diputado": "967"
      },
      {
        "nombre": "Martínez Herrera Joél Rubén",
        "id_diputado": "99"
      },
      {
        "nombre": "Martínez Juárez Christian Joél",
        "id_diputado": "921"
      },
      {
        "nombre": "Mazariegos López Nery René",
        "id_diputado": "845"
      },
      {
        "nombre": "Milian Gomez Sandra Yanet",
        "id_diputado": "886"
      },
      {
        "nombre": "Morataya Marroquín Evelyn Oddeth",
        "id_diputado": "828"
      },
      {
        "nombre": "Orellana Sandoval Jairo Danilo",
        "id_diputado": "923"
      },
      {
        "nombre": "Paz Rosales Karina Alexandra",
        "id_diputado": "160"
      },
      {
        "nombre": "Pereira Delgado Rudy Berner",
        "id_diputado": "117"
      },
      {
        "nombre": "Portillo Paz Julio César",
        "id_diputado": "974"
      },
      {
        "nombre": "Reyes Lee Fidel",
        "id_diputado": "128"
      },
      {
        "nombre": "Rivera Zaldaña  Shirley Joanna",
        "id_diputado": "785"
      },
      {
        "nombre": "Rodas Méndez Nery Mamfredo",
        "id_diputado": "931"
      },
      {
        "nombre": "Rosales Polanco Oswaldo",
        "id_diputado": "874"
      },
      {
        "nombre": "Tejeda Marroquín Byron Leonidas",
        "id_diputado": "887"
      },
      {
        "nombre": "Velásquez Pérez Mario",
        "id_diputado": "154"
      },
      {
        "nombre": "Ventura Urbina Luis Enrique",
        "id_diputado": "978"
      },
      {
        "nombre": "Villagrán Alvarez Jorge Mario",
        "id_diputado": "928"
      },
      {
        "nombre": "Villalta Pereira Olga Isabel",
        "id_diputado": "977"
      }
    ],
    "contra": [],
    "ausente": [
      {
        "nombre": "Aguirre Estrada Luis Fernando",
        "id_diputado": "929"
      },
      {
        "nombre": "Barrera Villanueva León Felipe",
        "id_diputado": "915"
      },
      {
        "nombre": "Blanco Lapola Orlando Joaquín",
        "id_diputado": "18"
      },
      {
        "nombre": "Cifuentes Ovalle Pablo Leonel",
        "id_diputado": "888"
      },
      {
        "nombre": "Escobar Castillo Kevyn Luis Carlo",
        "id_diputado": "926"
      },
      {
        "nombre": "España Cáceres Boris Roberto",
        "id_diputado": "54"
      },
      {
        "nombre": "Flores Divas Jairo Joaquín",
        "id_diputado": "61"
      },
      {
        "nombre": "García Barrios José Arnulfo",
        "id_diputado": "788"
      },
      {
        "nombre": "Illescas Sandoval David Mauricio",
        "id_diputado": "910"
      },
      {
        "nombre": "Javier Javier Esduín Jerson",
        "id_diputado": "892"
      },
      {
        "nombre": "Lam Ruano Francisco Vitelio",
        "id_diputado": "86"
      },
      {
        "nombre": "López Escobar Julio César",
        "id_diputado": "789"
      },
      {
        "nombre": "López Girón Carlos Enrique",
        "id_diputado": "976"
      },
      {
        "nombre": "Lucero Vásquez Jaime Octavio Augusto",
        "id_diputado": "93"
      },
      {
        "nombre": "Martínez Hernández Erick Geovany",
        "id_diputado": "793"
      },
      {
        "nombre": "Orellana Cruz Sandra Carolina",
        "id_diputado": "790"
      },
      {
        "nombre": "Rodríguez Palacios Byron Bladimiro",
        "id_diputado": "952"
      },
      {
        "nombre": "Toledo Cruz José Diego",
        "id_diputado": "960"
      }
    ],
    "abstencion": []
  },
  "totales": {
    "favor": 40,
    "contra": 0,
    "ausente": 18,
    "abstencion": 0
  }
}